LICENSE
MANIFEST.in
README.md
namedthreads-init.pth
namedthreads.py
setup.py
namedthreads.egg-info/PKG-INFO
namedthreads.egg-info/SOURCES.txt
namedthreads.egg-info/dependency_links.txt
namedthreads.egg-info/not-zip-safe
namedthreads.egg-info/top_level.txt