Metadata-Version: 2.1
Name: namedthreads
Version: 1.0
Summary: Patch to propagate Python thread names to system thread names
Home-page: https://github.com/beniwohli/namedthreads
Author: Benjamin Wohlwend
Author-email: piquadrat@gmail.com
License: BSD
Platform: OS Independent
Classifier: Development Status :: 4 - Beta
Classifier: Intended Audience :: Developers
Classifier: License :: OSI Approved :: BSD License
Classifier: Operating System :: OS Independent
Classifier: Programming Language :: Python
Classifier: Topic :: Internet :: WWW/HTTP
